{"architecture": "launch_vehicle", "prop_type": "electrical", "deployment_strategy": "one_plane_at_a_time_sequential", "verbose": true, "constellation_name": "My Constellation", "target_mass": 100.0, "target_volume": 1.0, "n_planes": 10, "n_sats_per_plane": 15, "plane_distribution_angle": 180, "n_sats_simultaneously_deployed": 5, "launcher": "Ariane_62", "launch_site": "Korou", "orbit_type": "LEO", "dispenser_tech_level": 1.0, "custom_launcher_name": null, "custom_launcher_performance": null, "fairing_diameter": null, "fairing_cylinder_height": null, "fairing_total_height": null, "interpolation_method": "linear", "a_client_insertion": 400.0, "ecc_client_insertion": 0.0, "inc_client_insertion": 90.0, "a_client_operational": 402.0, "ecc_client_operational": 0.0, "inc_client_operational": 90.0, "a_launcher_insertion": null, "ecc_launcher_insertion": null, "inc_launcher_insertion": null, "scenario_id": "7e0af378-4dbe-44ab-8c1e-50f532f18253", "config_run_id": 8, "data_path": "/Users/orell.buehler/Documents/github/tcat/DATA/tcat-data/7e0af378-4dbe-44ab-8c1e-50f532f18253/8"}